{
    "type": "mekanism:mek_data",
    "key": {
        "A": {
            "tag": "evolvedmekanism:alloys/exoversal"
        },
        "C": {
            "tag": "forge:circuits/creative"
        },
        "I": {
            "item": "minecraft:nether_star"
        },
        "P": {
            "item": "evolvedmekanism:dense_infusing_factory"
        }
    },
    "pattern": [
        "ACA",
        "IPI",
        "ACA"
    ],
    "result": {
        "item": "evolvedmekanism:creative_infusing_factory"
    }
}