{
    "variants": {
        "facing=north,active=false": {
            "model": "evolvedmekanism:block/factory/solidifying/dense"
        },
        "facing=south,active=false": {
            "model": "evolvedmekanism:block/factory/solidifying/dense",
            "y": 180
        },
        "facing=east,active=false": {
            "model": "evolvedmekanism:block/factory/solidifying/dense",
            "y": 90
        },
        "facing=west,active=false": {
            "model": "evolvedmekanism:block/factory/solidifying/dense",
            "y": -90
        },
        "facing=north,active=true": {
            "model": "evolvedmekanism:block/factory/solidifying/active/dense"
        },
        "facing=south,active=true": {
            "model": "evolvedmekanism:block/factory/solidifying/active/dense",
            "y": 180
        },
        "facing=east,active=true": {
            "model": "evolvedmekanism:block/factory/solidifying/active/dense",
            "y": 90
        },
        "facing=west,active=true": {
            "model": "evolvedmekanism:block/factory/solidifying/active/dense",
            "y": -90
        }
    }
}