{
    "type": "evolvedmekanism:solidifying",
    "input": {
        "ingredient": {
            "item": "evolvedmekanism:mold_rod"
        }
    },
    "fluidInput": {
        "fluid": "evolvedmekanism:molten_nether_star",
        "amount": 72
    },
    "extraInput": {
        "fluid": "mekanism:oxygen",
        "amount": 72
    },
    "output": {
        "tag": "forge:rods/nether_star"
    },
    "conditions": [
        {
            "type": "forge:not",
            "value": {
                "type": "forge:tag_empty",
                "tag": "forge:rods/nether_star"
            }
        }
    ]
}