{
  "type": "evolvedmekanism:solidifying",
  "duration": 30,
  "item_input": {
    "item": "evolvedmekanism:mold_rod"
  },
  "fluid_input": {
    "fluid": "evolvedmekanism:molten_infused_iron",
    "amount": 72
  },
  "extra_input": {
    "fluid": "mekanism:oxygen",
    "amount": 72
  },
  "output": {
    "tag": "c:rods/infused_iron"
  },
  "conditions": [
    {
      "type": "neoforge:not",
      "value": {
        "type": "neoforge:tag_empty",
        "tag": "c:rods/infused_iron"
      }
    }
  ]
}