{
    "type": "evolvedmekanism:solidifying",
    "input": {
        "ingredient": {
            "item": "evolvedmekanism:mold_plate"
        }
    },
    "fluidInput": {
        "fluid": "evolvedmekanism:molten_better_gold",
        "amount": 144
    },
    "extraInput": {
        "fluid": "mekanism:oxygen",
        "amount": 144
    },
    "output": {
        "tag": "forge:plates/better_gold"
    },
    "conditions": [
        {
            "type": "forge:not",
            "value": {
                "type": "forge:tag_empty",
                "tag": "forge:plates/better_gold"
            }
        }
    ]
}