{
    "type": "evolvedmekanism:solidifying",
    "duration": 60,
    "itemInput": {
        "ingredient": {
            "item": "evolvedmekanism:mold_ingot"
        }
    },
    "fluidInput": {
        "fluid": "evolvedmekanism:molten_stratus",
        "amount": 144
    },
    "extraInput": {
        "fluid": "mekanism:oxygen",
        "amount": 144
    },
    "output": {
        "tag": "c:ingots/stratus"
    },
    "conditions": [
        {
            "type": "neoforge:not",
            "value": {
                "type": "neoforge:tag_empty",
                "tag": "c:ingots/stratus"
            }
        }
    ]
}